{"clustering_algorithm__name": "HDBSCAN", "reduction_algorithm__name": "UMAP", "bertopic__top_n_words": 15, "bertopic__n_gram_range": "(2,2)", "bertopic__min_topic_size": 20, "bertopic__diversity": 0.2997671830607806, "bertopic__outliers_threshold": 0.04538353047740054, "bertopic__nr_topics": 17, "hdbscan__min_cluster_size": 13, "hdbscan__cluster_selection_epsilon": 0.27587067496711104, "umap__n_neighbors": 14, "umap__n_components": 5, "umap__metric": "cosine", "umap__min_dist": 0.7173485304812026, "umap__spread": 0.7042355458623331}